[
    {
        "id": 1,
        "name": "ENGINE DIAGNOSTIC",
        "price": "300",
        "description": "Lorem ipsum dolor sit amet consectetur adipisicing elit. Quibusdam non rerum architecto quod dolorum atque saepe minima beatae tempora illo!",
        "img": "https://i.ibb.co/D9ms7gQ/1.jpg"
    },
    {
        "id": 2,
        "name": "WHEEL ALIGNMENT",
        "price": "100",
        "description": "Lorem ipsum dolor sit amet consectetur adipisicing elit. Quibusdam non rerum architecto quod dolorum atque saepe minima beatae tempora illo!",
        "img": "https://i.ibb.co/L5TbRLn/2.jpg"
    },
    {
        "id": 3,
        "name": "OIL CHANGING",
        "price": "150",
        "description": "Lorem ipsum dolor sit amet consectetur adipisicing elit. Quibusdam non rerum architecto quod dolorum atque saepe minima beatae tempora illo!",
        "img": "https://i.ibb.co/fdvMyx2/3.jpg"
    },
    {
        "id": 4,
        "name": "BRAKE REPAIRING",
        "price": "180",
        "description": "Lorem ipsum dolor sit amet consectetur adipisicing elit. Quibusdam non rerum architecto quod dolorum atque saepe minima beatae tempora illo!",
        "img": "https://i.ibb.co/NZk5Sb0/4.jpg"
    },
    {
        "id": 5,
        "name": "WASH AND GLASSING",
        "price": "100",
        "description": "Lorem ipsum dolor sit amet consectetur adipisicing elit. Quibusdam non rerum architecto quod dolorum atque saepe minima beatae tempora illo!",
        "img": "https://i.ibb.co/7JSG3cB/5.jpg"
    },
    {
        "id": 6,
        "name": "COMPLETE ANALYSIS",
        "price": "300",
        "description": "Lorem ipsum dolor sit amet consectetur adipisicing elit. Quibusdam non rerum architecto quod dolorum atque saepe minima beatae tempora illo!",
        "img": "https://i.ibb.co/qsGk7ZZ/6.jpg"
    }
]
